Workbook

Sheet Dashboard
A1: TRABFLOW — MODELO FINANCIERO
A2: Resumen ejecutivo · TrabFlow Technologies, S.L. · Junio 2026
A4: Clientes · cierre Año 3 (Base) | B4: ARR · cierre Año 3 (Base) | C4: EBITDA incl. CAC · Año 3 (Base) | D4: Ratio LTV:CAC (Base) | E4: Payback CAC · meses (Base)
A5: =Mensual_Base!B40 -> 540.94753 | B5: =Escenarios!C7 -> 318077.15 | C5: ='P&L Anual'!I11 -> 191675.84 | D5: ='Unit Economics'!C13 -> 18.333333 | E5: ='Unit Economics'!C14 -> 2.7272727
A7: Crecimiento de MRR a 36 meses, por escenario
A28: ARR de cierre por año y escenario | F28: Asignación del capital por tramo (Use of Funds)

Sheet Supuestos
A1: SUPUESTOS DEL MODELO
A2: TrabFlow Technologies, S.L. · Modelo financiero a 3 años · Junio 2026
A4: Todas las celdas en azul son entradas editables. El resto de hojas calcula a partir de estos supuestos: cambiar un valor aquí recalcula todo el modelo.
A6: Parámetro | B6: Conservador | C6: Base | D6: Agresivo | E6: Unidad | F6: Fuente / Nota
A7: Clientes iniciales | B7: 50 | C7: 50 | D7: 50 | E7: clientes | F7: Cartera de partida estimada por el fundador (sin datos de cliente de pago auditados aún).
A8: Altas netas mensuales | B8: 10 | C8: 20 | D8: 45 | E8: clientes/mes | F8: Ritmo de adquisición mensual constante asumido. Base = hipótesis inicial del fundador; Conservador/Agresivo = sensibilidad ±.
A9: Churn mensual | B9: 0.035 | C9: 0.02 | D9: 0.015 | E9: % | F9: Referencia de mercado SaaS vertical SMB (1,5–3,5% mensual). Pendiente de validar con cohortes reales de TrabFlow.
A10: ARPU mensual | B10: 45 | C10: 49 | D10: 60 | E10: €/cliente/mes | F10: Base = precio público del plan Profesional (49€/mes). Agresivo asume mayor mezcla hacia planes Empresa (89€) y Empresa+ (179€).
A11: CAC | B11: 150 | C11: 120 | D11: 95 | E11: €/cliente | F11: Coste de adquisición por cliente. Mejora en el escenario Agresivo por eficiencia de canal (gremios/referidos) a escala. Hipótesis de modelo, no medido aún.
A12: Coste IA / infraestructura | B12: 5 | C12: 5 | D12: 5 | E12: €/cliente/mes | F12: Supabase + Claude API + Whisper STT, estimado por cliente activo.
A13: Costes fijos mensuales | B13: 3000 | C13: 3000 | D13: 3000 | E13: €/mes | F13: Estructura mínima actual (founder-led): herramientas, hosting base, gestoría, otros gastos fijos.
A15: Notas de revisión
A16: • Los escenarios Conservador y Agresivo se han reconstruido para que ARPU, CAC, churn y ritmo de altas se combinen de forma consistente; no son cifras objetivo fijadas a mano.
A17: • El EBITDA se muestra en dos versiones en la hoja P&L Anual: antes y después del coste de adquisición (CAC), porque el CAC es una decisión de inversión en crecimiento, no un coste fijo de operación.
A18: • CAC y churn son hipótesis de partida, no datos observados con clientes reales. Deben tratarse como rango de planificación, no como resultado garantizado.

Sheet Mensual_Conservador
A1: PROYECCIÓN MENSUAL — ESCENARIO CONSERVADOR
A2: 36 meses · todas las celdas son fórmulas ligadas a la hoja Supuestos
A3: Fuente de supuestos: hoja Supuestos, columna B (Conservador)
A4: Mes | B4: Clientes activos | C4: Altas netas | D4: MRR | E4: ARR (run-rate) | F4: Coste CAC | G4: Coste IA/infra | H4: Costes fijos | I4: Beneficio bruto | J4: EBITDA antes de CAC | K4: EBITDA incl. CAC
A5: 1 | B5: =Supuestos!$B$7*(1-Supuestos!$B$9)+Supuestos!$B$8 -> 58.25 | C5: =Supuestos!$B$8 -> 10 | D5: =B5*Supuestos!$B$10 -> 2621.25 | E5: =D5*12 -> 31455 | F5: =C5*Supuestos!$B$11 -> 1500 | G5: =B5*Supuestos!$B$12 -> 291.25 | H5: =Supuestos!$B$13 -> 3000 | I5: =D5-G5 -> 2330 | J5: =I5-H5 -> -670 | K5: =J5-F5 -> -2170
A6: 2 | B6: =B5*(1-Supuestos!$B$9)+Supuestos!$B$8 -> 66.21125 | C6: =Supuestos!$B$8 -> 10 | D6: =B6*Supuestos!$B$10 -> 2979.5062 | E6: =D6*12 -> 35754.075 | F6: =C6*Supuestos!$B$11 -> 1500 | G6: =B6*Supuestos!$B$12 -> 331.05625 | H6: =Supuestos!$B$13 -> 3000 | I6: =D6-G6 -> 2648.45 | J6: =I6-H6 -> -351.55 | K6: =J6-F6 -> -1851.55
A7: 3 | B7: =B6*(1-Supuestos!$B$9)+Supuestos!$B$8 -> 73.893856 | C7: =Supuestos!$B$8 -> 10 | D7: =B7*Supuestos!$B$10 -> 3325.2235 | E7: =D7*12 -> 39902.682 | F7: =C7*Supuestos!$B$11 -> 1500 | G7: =B7*Supuestos!$B$12 -> 369.46928 | H7: =Supuestos!$B$13 -> 3000 | I7: =D7-G7 -> 2955.7542 | J7: =I7-H7 -> -44.24575 | K7: =J7-F7 -> -1544.2458
A8: 4 | B8: =B7*(1-Supuestos!$B$9)+Supuestos!$B$8 -> 81.307571 | C8: =Supuestos!$B$8 -> 10 | D8: =B8*Supuestos!$B$10 -> 3658.8407 | E8: =D8*12 -> 43906.088 | F8: =C8*Supuestos!$B$11 -> 1500 | G8: =B8*Supuestos!$B$12 -> 406.53786 | H8: =Supuestos!$B$13 -> 3000 | I8: =D8-G8 -> 3252.3029 | J8: =I8-H8 -> 252.30285 | K8: =J8-F8 -> -1247.6971
A9: 5 | B9: =B8*(1-Supuestos!$B$9)+Supuestos!$B$8 -> 88.461806 | C9: =Supuestos!$B$8 -> 10 | D9: =B9*Supuestos!$B$10 -> 3980.7813 | E9: =D9*12 -> 47769.375 | F9: =C9*Supuestos!$B$11 -> 1500 | G9: =B9*Supuestos!$B$12 -> 442.30903 | H9: =Supuestos!$B$13 -> 3000 | I9: =D9-G9 -> 3538.4723 | J9: =I9-H9 -> 538.47225 | K9: =J9-F9 -> -961.52775
A10: 6 | B10: =B9*(1-Supuestos!$B$9)+Supuestos!$B$8 -> 95.365643 | C10: =Supuestos!$B$8 -> 10 | D10: =B10*Supuestos!$B$10 -> 4291.4539 | E10: =D10*12 -> 51497.447 | F10: =C10*Supuestos!$B$11 -> 1500 | G10: =B10*Supuestos!$B$12 -> 476.82822 | H10: =Supuestos!$B$13 -> 3000 | I10: =D10-G10 -> 3814.6257 | J10: =I10-H10 -> 814.62572 | K10: =J10-F10 -> -685.37428
A11: 7 | B11: =B10*(1-Supuestos!$B$9)+Supuestos!$B$8 -> 102.02785 | C11: =Supuestos!$B$8 -> 10 | D11: =B11*Supuestos!$B$10 -> 4591.2531 | E11: =D11*12 -> 55095.037 | F11: =C11*Supuestos!$B$11 -> 1500 | G11: =B11*Supuestos!$B$12 -> 510.13923 | H11: =Supuestos!$B$13 -> 3000 | I11: =D11-G11 -> 4081.1138 | J11: =I11-H11 -> 1081.1138 | K11: =J11-F11 -> -418.88618
A12: 8 | B12: =B11*(1-Supuestos!$B$9)+Supuestos!$B$8 -> 108.45687 | C12: =Supuestos!$B$8 -> 10 | D12: =B12*Supuestos!$B$10 -> 4880.5592 | E12: =D12*12 -> 58566.71 | F12: =C12*Supuestos!$B$11 -> 1500 | G12: =B12*Supuestos!$B$12 -> 542.28435 | H12: =Supuestos!$B$13 -> 3000 | I12: =D12-G12 -> 4338.2748 | J12: =I12-H12 -> 1338.2748 | K12: =J12-F12 -> -161.72516
A13: 9 | B13: =B12*(1-Supuestos!$B$9)+Supuestos!$B$8 -> 114.66088 | C13: =Supuestos!$B$8 -> 10 | D13: =B13*Supuestos!$B$10 -> 5159.7396 | E13: =D13*12 -> 61916.875 | F13: =C13*Supuestos!$B$11 -> 1500 | G13: =B13*Supuestos!$B$12 -> 573.3044 | H13: =Supuestos!$B$13 -> 3000 | I13: =D13-G13 -> 4586.4352 | J13: =I13-H13 -> 1586.4352 | K13: =J13-F13 -> 86.435219
A14: 10 | B14: =B13*(1-Supuestos!$B$9)+Supuestos!$B$8 -> 120.64775 | C14: =Supuestos!$B$8 -> 10 | D14: =B14*Supuestos!$B$10 -> 5429.1487 | E14: =D14*12 -> 65149.785 | F14: =C14*Supuestos!$B$11 -> 1500 | G14: =B14*Supuestos!$B$12 -> 603.23875 | H14: =Supuestos!$B$13 -> 3000 | I14: =D14-G14 -> 4825.91 | J14: =I14-H14 -> 1825.91 | K14: =J14-F14 -> 325.90999
A15: 11 | B15: =B14*(1-Supuestos!$B$9)+Supuestos!$B$8 -> 126.42508 | C15: =Supuestos!$B$8 -> 10 | D15: =B15*Supuestos!$B$10 -> 5689.1285 | E15: =D15*12 -> 68269.542 | F15: =C15*Supuestos!$B$11 -> 1500 | G15: =B15*Supuestos!$B$12 -> 632.12539 | H15: =Supuestos!$B$13 -> 3000 | I15: =D15-G15 -> 5057.0031 | J15: =I15-H15 -> 2057.0031 | K15: =J15-F15 -> 557.00314
A16: 12 | B16: =B15*(1-Supuestos!$B$9)+Supuestos!$B$8 -> 132.0002 | C16: =Supuestos!$B$8 -> 10 | D16: =B16*Supuestos!$B$10 -> 5940.009 | E16: =D16*12 -> 71280.108 | F16: =C16*Supuestos!$B$11 -> 1500 | G16: =B16*Supuestos!$B$12 -> 660.001 | H16: =Supuestos!$B$13 -> 3000 | I16: =D16-G16 -> 5280.008 | J16: =I16-H16 -> 2280.008 | K16: =J16-F16 -> 780.00803
A17: 13 | B17: =B16*(1-Supuestos!$B$9)+Supuestos!$B$8 -> 137.38019 | C17: =Supuestos!$B$8 -> 10 | D17: =B17*Supuestos!$B$10 -> 6182.1087 | E17: =D17*12 -> 74185.305 | F17: =C17*Supuestos!$B$11 -> 1500 | G17: =B17*Supuestos!$B$12 -> 686.90097 | H17: =Supuestos!$B$13 -> 3000 | I17: =D17-G17 -> 5495.2077 | J17: =I17-H17 -> 2495.2077 | K17: =J17-F17 -> 995.20775
... A40: 36 | B40: =B39*(1-Supuestos!$B$9)+Supuestos!$B$8 -> 220.34569 | C40: =Supuestos!$B$8 -> 10 | D40: =B40*Supuestos!$B$10 -> 9915.5559 | E40: =D40*12 -> 118986.67 | F40: =C40*Supuestos!$B$11 -> 1500 | G40: =B40*Supuestos!$B$12 -> 1101.7284 | H40: =Supuestos!$B$13 -> 3000 | I40: =D40-G40 -> 8813.8274 | J40: =I40-H40 -> 5813.8274 | K40: =J40-F40 -> 4313.8274

Sheet Mensual_Base
A1: PROYECCIÓN MENSUAL — ESCENARIO BASE
A2: 36 meses · todas las celdas son fórmulas ligadas a la hoja Supuestos
A3: Fuente de supuestos: hoja Supuestos, columna C (Base)
A4: Mes | B4: Clientes activos | C4: Altas netas | D4: MRR | E4: ARR (run-rate) | F4: Coste CAC | G4: Coste IA/infra | H4: Costes fijos | I4: Beneficio bruto | J4: EBITDA antes de CAC | K4: EBITDA incl. CAC
A5: 1 | B5: =Supuestos!$C$7*(1-Supuestos!$C$9)+Supuestos!$C$8 -> 69 | C5: =Supuestos!$C$8 -> 20 | D5: =B5*Supuestos!$C$10 -> 3381 | E5: =D5*12 -> 40572 | F5: =C5*Supuestos!$C$11 -> 2400 | G5: =B5*Supuestos!$C$12 -> 345 | H5: =Supuestos!$C$13 -> 3000 | I5: =D5-G5 -> 3036 | J5: =I5-H5 -> 36 | K5: =J5-F5 -> -2364
A6: 2 | B6: =B5*(1-Supuestos!$C$9)+Supuestos!$C$8 -> 87.62 | C6: =Supuestos!$C$8 -> 20 | D6: =B6*Supuestos!$C$10 -> 4293.38 | E6: =D6*12 -> 51520.56 | F6: =C6*Supuestos!$C$11 -> 2400 | G6: =B6*Supuestos!$C$12 -> 438.1 | H6: =Supuestos!$C$13 -> 3000 | I6: =D6-G6 -> 3855.28 | J6: =I6-H6 -> 855.28 | K6: =J6-F6 -> -1544.72
A7: 3 | B7: =B6*(1-Supuestos!$C$9)+Supuestos!$C$8 -> 105.8676 | C7: =Supuestos!$C$8 -> 20 | D7: =B7*Supuestos!$C$10 -> 5187.5124 | E7: =D7*12 -> 62250.149 | F7: =C7*Supuestos!$C$11 -> 2400 | G7: =B7*Supuestos!$C$12 -> 529.338 | H7: =Supuestos!$C$13 -> 3000 | I7: =D7-G7 -> 4658.1744 | J7: =I7-H7 -> 1658.1744 | K7: =J7-F7 -> -741.8256
A8: 4 | B8: =B7*(1-Supuestos!$C$9)+Supuestos!$C$8 -> 123.75025 | C8: =Supuestos!$C$8 -> 20 | D8: =B8*Supuestos!$C$10 -> 6063.7622 | E8: =D8*12 -> 72765.146 | F8: =C8*Supuestos!$C$11 -> 2400 | G8: =B8*Supuestos!$C$12 -> 618.75124 | H8: =Supuestos!$C$13 -> 3000 | I8: =D8-G8 -> 5445.0109 | J8: =I8-H8 -> 2445.0109 | K8: =J8-F8 -> 45.010912
A9: 5 | B9: =B8*(1-Supuestos!$C$9)+Supuestos!$C$8 -> 141.27524 | C9: =Supuestos!$C$8 -> 20 | D9: =B9*Supuestos!$C$10 -> 6922.4869 | E9: =D9*12 -> 83069.843 | F9: =C9*Supuestos!$C$11 -> 2400 | G9: =B9*Supuestos!$C$12 -> 706.37622 | H9: =Supuestos!$C$13 -> 3000 | I9: =D9-G9 -> 6216.1107 | J9: =I9-H9 -> 3216.1107 | K9: =J9-F9 -> 816.11069
A10: 6 | B10: =B9*(1-Supuestos!$C$9)+Supuestos!$C$8 -> 158.44974 | C10: =Supuestos!$C$8 -> 20 | D10: =B10*Supuestos!$C$10 -> 7764.0372 | E10: =D10*12 -> 93168.446 | F10: =C10*Supuestos!$C$11 -> 2400 | G10: =B10*Supuestos!$C$12 -> 792.24869 | H10: =Supuestos!$C$13 -> 3000 | I10: =D10-G10 -> 6971.7885 | J10: =I10-H10 -> 3971.7885 | K10: =J10-F10 -> 1571.7885
A11: 7 | B11: =B10*(1-Supuestos!$C$9)+Supuestos!$C$8 -> 175.28074 | C11: =Supuestos!$C$8 -> 20 | D11: =B11*Supuestos!$C$10 -> 8588.7564 | E11: =D11*12 -> 103065.08 | F11: =C11*Supuestos!$C$11 -> 2400 | G11: =B11*Supuestos!$C$12 -> 876.40372 | H11: =Supuestos!$C$13 -> 3000 | I11: =D11-G11 -> 7712.3527 | J11: =I11-H11 -> 4712.3527 | K11: =J11-F11 -> 2312.3527
A12: 8 | B12: =B11*(1-Supuestos!$C$9)+Supuestos!$C$8 -> 191.77513 | C12: =Supuestos!$C$8 -> 20 | D12: =B12*Supuestos!$C$10 -> 9396.9813 | E12: =D12*12 -> 112763.78 | F12: =C12*Supuestos!$C$11 -> 2400 | G12: =B12*Supuestos!$C$12 -> 958.87564 | H12: =Supuestos!$C$13 -> 3000 | I12: =D12-G12 -> 8438.1057 | J12: =I12-H12 -> 5438.1057 | K12: =J12-F12 -> 3038.1057
A13: 9 | B13: =B12*(1-Supuestos!$C$9)+Supuestos!$C$8 -> 207.93963 | C13: =Supuestos!$C$8 -> 20 | D13: =B13*Supuestos!$C$10 -> 10189.042 | E13: =D13*12 -> 122268.5 | F13: =C13*Supuestos!$C$11 -> 2400 | G13: =B13*Supuestos!$C$12 -> 1039.6981 | H13: =Supuestos!$C$13 -> 3000 | I13: =D13-G13 -> 9149.3435 | J13: =I13-H13 -> 6149.3435 | K13: =J13-F13 -> 3749.3435
A14: 10 | B14: =B13*(1-Supuestos!$C$9)+Supuestos!$C$8 -> 223.78083 | C14: =Supuestos!$C$8 -> 20 | D14: =B14*Supuestos!$C$10 -> 10965.261 | E14: =D14*12 -> 131583.13 | F14: =C14*Supuestos!$C$11 -> 2400 | G14: =B14*Supuestos!$C$12 -> 1118.9042 | H14: =Supuestos!$C$13 -> 3000 | I14: =D14-G14 -> 9846.3567 | J14: =I14-H14 -> 6846.3567 | K14: =J14-F14 -> 4446.3567
A15: 11 | B15: =B14*(1-Supuestos!$C$9)+Supuestos!$C$8 -> 239.30522 | C15: =Supuestos!$C$8 -> 20 | D15: =B15*Supuestos!$C$10 -> 11725.956 | E15: =D15*12 -> 140711.47 | F15: =C15*Supuestos!$C$11 -> 2400 | G15: =B15*Supuestos!$C$12 -> 1196.5261 | H15: =Supuestos!$C$13 -> 3000 | I15: =D15-G15 -> 10529.43 | J15: =I15-H15 -> 7529.4295 | K15: =J15-F15 -> 5129.4295
A16: 12 | B16: =B15*(1-Supuestos!$C$9)+Supuestos!$C$8 -> 254.51911 | C16: =Supuestos!$C$8 -> 20 | D16: =B16*Supuestos!$C$10 -> 12471.437 | E16: =D16*12 -> 149657.24 | F16: =C16*Supuestos!$C$11 -> 2400 | G16: =B16*Supuestos!$C$12 -> 1272.5956 | H16: =Supuestos!$C$13 -> 3000 | I16: =D16-G16 -> 11198.841 | J16: =I16-H16 -> 8198.8409 | K16: =J16-F16 -> 5798.8409
A17: 13 | B17: =B16*(1-Supuestos!$C$9)+Supuestos!$C$8 -> 269.42873 | C17: =Supuestos!$C$8 -> 20 | D17: =B17*Supuestos!$C$10 -> 13202.008 | E17: =D17*12 -> 158424.09 | F17: =C17*Supuestos!$C$11 -> 2400 | G17: =B17*Supuestos!$C$12 -> 1347.1437 | H17: =Supuestos!$C$13 -> 3000 | I17: =D17-G17 -> 11854.864 | J17: =I17-H17 -> 8854.8641 | K17: =J17-F17 -> 6454.8641
... A40: 36 | B40: =B39*(1-Supuestos!$C$9)+Supuestos!$C$8 -> 540.94753 | C40: =Supuestos!$C$8 -> 20 | D40: =B40*Supuestos!$C$10 -> 26506.429 | E40: =D40*12 -> 318077.15 | F40: =C40*Supuestos!$C$11 -> 2400 | G40: =B40*Supuestos!$C$12 -> 2704.7376 | H40: =Supuestos!$C$13 -> 3000 | I40: =D40-G40 -> 23801.691 | J40: =I40-H40 -> 20801.691 | K40: =J40-F40 -> 18401.691

Sheet Mensual_Agresivo
A1: PROYECCIÓN MENSUAL — ESCENARIO AGRESIVO
A2: 36 meses · todas las celdas son fórmulas ligadas a la hoja Supuestos
A3: Fuente de supuestos: hoja Supuestos, columna D (Agresivo)
A4: Mes | B4: Clientes activos | C4: Altas netas | D4: MRR | E4: ARR (run-rate) | F4: Coste CAC | G4: Coste IA/infra | H4: Costes fijos | I4: Beneficio bruto | J4: EBITDA antes de CAC | K4: EBITDA incl. CAC
A5: 1 | B5: =Supuestos!$D$7*(1-Supuestos!$D$9)+Supuestos!$D$8 -> 94.25 | C5: =Supuestos!$D$8 -> 45 | D5: =B5*Supuestos!$D$10 -> 5655 | E5: =D5*12 -> 67860 | F5: =C5*Supuestos!$D$11 -> 4275 | G5: =B5*Supuestos!$D$12 -> 471.25 | H5: =Supuestos!$D$13 -> 3000 | I5: =D5-G5 -> 5183.75 | J5: =I5-H5 -> 2183.75 | K5: =J5-F5 -> -2091.25
A6: 2 | B6: =B5*(1-Supuestos!$D$9)+Supuestos!$D$8 -> 137.83625 | C6: =Supuestos!$D$8 -> 45 | D6: =B6*Supuestos!$D$10 -> 8270.175 | E6: =D6*12 -> 99242.1 | F6: =C6*Supuestos!$D$11 -> 4275 | G6: =B6*Supuestos!$D$12 -> 689.18125 | H6: =Supuestos!$D$13 -> 3000 | I6: =D6-G6 -> 7580.9937 | J6: =I6-H6 -> 4580.9937 | K6: =J6-F6 -> 305.99375
A7: 3 | B7: =B6*(1-Supuestos!$D$9)+Supuestos!$D$8 -> 180.76871 | C7: =Supuestos!$D$8 -> 45 | D7: =B7*Supuestos!$D$10 -> 10846.122 | E7: =D7*12 -> 130153.47 | F7: =C7*Supuestos!$D$11 -> 4275 | G7: =B7*Supuestos!$D$12 -> 903.84353 | H7: =Supuestos!$D$13 -> 3000 | I7: =D7-G7 -> 9942.2788 | J7: =I7-H7 -> 6942.2788 | K7: =J7-F7 -> 2667.2788
A8: 4 | B8: =B7*(1-Supuestos!$D$9)+Supuestos!$D$8 -> 223.05718 | C8: =Supuestos!$D$8 -> 45 | D8: =B8*Supuestos!$D$10 -> 13383.431 | E8: =D8*12 -> 160601.17 | F8: =C8*Supuestos!$D$11 -> 4275 | G8: =B8*Supuestos!$D$12 -> 1115.2859 | H8: =Supuestos!$D$13 -> 3000 | I8: =D8-G8 -> 12268.145 | J8: =I8-H8 -> 9268.1447 | K8: =J8-F8 -> 4993.1447
A9: 5 | B9: =B8*(1-Supuestos!$D$9)+Supuestos!$D$8 -> 264.71132 | C9: =Supuestos!$D$8 -> 45 | D9: =B9*Supuestos!$D$10 -> 15882.679 | E9: =D9*12 -> 190592.15 | F9: =C9*Supuestos!$D$11 -> 4275 | G9: =B9*Supuestos!$D$12 -> 1323.5566 | H9: =Supuestos!$D$13 -> 3000 | I9: =D9-G9 -> 14559.122 | J9: =I9-H9 -> 11559.122 | K9: =J9-F9 -> 7284.1225
A10: 6 | B10: =B9*(1-Supuestos!$D$9)+Supuestos!$D$8 -> 305.74065 | C10: =Supuestos!$D$8 -> 45 | D10: =B10*Supuestos!$D$10 -> 18344.439 | E10: =D10*12 -> 220133.27 | F10: =C10*Supuestos!$D$11 -> 4275 | G10: =B10*Supuestos!$D$12 -> 1528.7032 | H10: =Supuestos!$D$13 -> 3000 | I10: =D10-G10 -> 16815.736 | J10: =I10-H10 -> 13815.736 | K10: =J10-F10 -> 9540.7357
A11: 7 | B11: =B10*(1-Supuestos!$D$9)+Supuestos!$D$8 -> 346.15454 | C11: =Supuestos!$D$8 -> 45 | D11: =B11*Supuestos!$D$10 -> 20769.272 | E11: =D11*12 -> 249231.27 | F11: =C11*Supuestos!$D$11 -> 4275 | G11: =B11*Supuestos!$D$12 -> 1730.7727 | H11: =Supuestos!$D$13 -> 3000 | I11: =D11-G11 -> 19038.5 | J11: =I11-H11 -> 16038.5 | K11: =J11-F11 -> 11763.5
A12: 8 | B12: =B11*(1-Supuestos!$D$9)+Supuestos!$D$8 -> 385.96222 | C12: =Supuestos!$D$8 -> 45 | D12: =B12*Supuestos!$D$10 -> 23157.733 | E12: =D12*12 -> 277892.8 | F12: =C12*Supuestos!$D$11 -> 4275 | G12: =B12*Supuestos!$D$12 -> 1929.8111 | H12: =Supuestos!$D$13 -> 3000 | I12: =D12-G12 -> 21227.922 | J12: =I12-H12 -> 18227.922 | K12: =J12-F12 -> 13952.922
A13: 9 | B13: =B12*(1-Supuestos!$D$9)+Supuestos!$D$8 -> 425.17279 | C13: =Supuestos!$D$8 -> 45 | D13: =B13*Supuestos!$D$10 -> 25510.367 | E13: =D13*12 -> 306124.41 | F13: =C13*Supuestos!$D$11 -> 4275 | G13: =B13*Supuestos!$D$12 -> 2125.8639 | H13: =Supuestos!$D$13 -> 3000 | I13: =D13-G13 -> 23384.503 | J13: =I13-H13 -> 20384.503 | K13: =J13-F13 -> 16109.503
A14: 10 | B14: =B13*(1-Supuestos!$D$9)+Supuestos!$D$8 -> 463.7952 | C14: =Supuestos!$D$8 -> 45 | D14: =B14*Supuestos!$D$10 -> 27827.712 | E14: =D14*12 -> 333932.54 | F14: =C14*Supuestos!$D$11 -> 4275 | G14: =B14*Supuestos!$D$12 -> 2318.976 | H14: =Supuestos!$D$13 -> 3000 | I14: =D14-G14 -> 25508.736 | J14: =I14-H14 -> 22508.736 | K14: =J14-F14 -> 18233.736
A15: 11 | B15: =B14*(1-Supuestos!$D$9)+Supuestos!$D$8 -> 501.83827 | C15: =Supuestos!$D$8 -> 45 | D15: =B15*Supuestos!$D$10 -> 30110.296 | E15: =D15*12 -> 361323.55 | F15: =C15*Supuestos!$D$11 -> 4275 | G15: =B15*Supuestos!$D$12 -> 2509.1913 | H15: =Supuestos!$D$13 -> 3000 | I15: =D15-G15 -> 27601.105 | J15: =I15-H15 -> 24601.105 | K15: =J15-F15 -> 20326.105
A16: 12 | B16: =B15*(1-Supuestos!$D$9)+Supuestos!$D$8 -> 539.31069 | C16: =Supuestos!$D$8 -> 45 | D16: =B16*Supuestos!$D$10 -> 32358.642 | E16: =D16*12 -> 388303.7 | F16: =C16*Supuestos!$D$11 -> 4275 | G16: =B16*Supuestos!$D$12 -> 2696.5535 | H16: =Supuestos!$D$13 -> 3000 | I16: =D16-G16 -> 29662.088 | J16: =I16-H16 -> 26662.088 | K16: =J16-F16 -> 22387.088
A17: 13 | B17: =B16*(1-Supuestos!$D$9)+Supuestos!$D$8 -> 576.22103 | C17: =Supuestos!$D$8 -> 45 | D17: =B17*Supuestos!$D$10 -> 34573.262 | E17: =D17*12 -> 414879.14 | F17: =C17*Supuestos!$D$11 -> 4275 | G17: =B17*Supuestos!$D$12 -> 2881.1052 | H17: =Supuestos!$D$13 -> 3000 | I17: =D17-G17 -> 31692.157 | J17: =I17-H17 -> 28692.157 | K17: =J17-F17 -> 24417.157
... A40: 36 | B40: =B39*(1-Supuestos!$D$9)+Supuestos!$D$8 -> 1287.9111 | C40: =Supuestos!$D$8 -> 45 | D40: =B40*Supuestos!$D$10 -> 77274.665 | E40: =D40*12 -> 927295.99 | F40: =C40*Supuestos!$D$11 -> 4275 | G40: =B40*Supuestos!$D$12 -> 6439.5555 | H40: =Supuestos!$D$13 -> 3000 | I40: =D40-G40 -> 70835.11 | J40: =I40-H40 -> 67835.11 | K40: =J40-F40 -> 63560.11

Sheet P&L Anual
A1: CUENTA DE RESULTADOS ANUAL · 3 ESCENARIOS
A2: EBITDA antes de CAC = ingresos − coste de IA/infraestructura − costes fijos (excluye inversión en adquisición). EBITDA incl. CAC resta además el gasto de adquisición de clientes del propio año.
A4: Escenario | B4: Año | C4: Ingresos | D4: Coste IA/infra | E4: Costes fijos | F4: Coste CAC | G4: EBITDA antes de CAC | H4: Margen (antes CAC) | I4: EBITDA incl. CAC | J4: Margen (incl. CAC)
A5: Conservador | B5: Año 1 | C5: =SUM(Mensual_Conservador!D5:D16) -> 52546.894 | D5: =SUM(Mensual_Conservador!G5:G16) -> 5838.5438 | E5: =SUM(Mensual_Conservador!H5:H16) -> 36000 | F5: =SUM(Mensual_Conservador!F5:F16) -> 18000 | G5: =C5-D5-E5 -> 10708.35 | H5: =G5/C5 -> 0.20378655 | I5: =G5-F5 -> -7291.6499 | J5: =I5/C5 -> -0.13876462
A6: Conservador | B6: Año 2 | C6: =SUM(Mensual_Conservador!D17:D28) -> 87939.758 | D6: =SUM(Mensual_Conservador!G17:G28) -> 9771.0842 | E6: =SUM(Mensual_Conservador!H17:H28) -> 36000 | F6: =SUM(Mensual_Conservador!F17:F28) -> 18000 | G6: =C6-D6-E6 -> 42168.674 | H6: =G6/C6 -> 0.47951774 | I6: =G6-F6 -> 24168.674 | J6: =I6/C6 -> 0.27483216
A7: Conservador | B7: Año 3 | C7: =SUM(Mensual_Conservador!D29:D40) -> 111020.17 | D7: =SUM(Mensual_Conservador!G29:G40) -> 12335.574 | E7: =SUM(Mensual_Conservador!H29:H40) -> 36000 | F7: =SUM(Mensual_Conservador!F29:F40) -> 18000 | G7: =C7-D7-E7 -> 62684.591 | H7: =G7/C7 -> 0.56462347 | I7: =G7-F7 -> 44684.591 | J7: =I7/C7 -> 0.40249077
A9: Base | B9: Año 1 | C9: =SUM(Mensual_Base!D5:D16) -> 96949.611 | D9: =SUM(Mensual_Base!G5:G16) -> 9892.8174 | E9: =SUM(Mensual_Base!H5:H16) -> 36000 | F9: =SUM(Mensual_Base!F5:F16) -> 28800 | G9: =C9-D9-E9 -> 51056.794 | H9: =G9/C9 -> 0.52663227 | I9: =G9-F9 -> 22256.794 | J9: =I9/C9 -> 0.22957074
A10: Base | B10: Año 2 | C10: =SUM(Mensual_Base!D17:D28) -> 202664.55 | D10: =SUM(Mensual_Base!G17:G28) -> 20680.056 | E10: =SUM(Mensual_Base!H17:H28) -> 36000 | F10: =SUM(Mensual_Base!F17:F28) -> 28800 | G10: =C10-D10-E10 -> 145984.49 | H10: =G10/C10 -> 0.72032575 | I10: =G10-F10 -> 117184.49 | J10: =I10/C10 -> 0.578219
A11: Base | B11: Año 3 | C11: =SUM(Mensual_Base!D29:D40) -> 285620.83 | D11: =SUM(Mensual_Base!G29:G40) -> 29144.982 | E11: =SUM(Mensual_Base!H29:H40) -> 36000 | F11: =SUM(Mensual_Base!F29:F40) -> 28800 | G11: =C11-D11-E11 -> 220475.84 | H11: =G11/C11 -> 0.77191795 | I11: =G11-F11 -> 191675.84 | J11: =I11/C11 -> 0.67108497
A13: Agresivo | B13: Año 1 | C13: =SUM(Mensual_Agresivo!D5:D16) -> 232115.87 | D13: =SUM(Mensual_Agresivo!G5:G16) -> 19342.989 | E13: =SUM(Mensual_Agresivo!H5:H16) -> 36000 | F13: =SUM(Mensual_Agresivo!F5:F16) -> 51300 | G13: =C13-D13-E13 -> 176772.88 | H13: =G13/C13 -> 0.76157171 | I13: =G13-F13 -> 125472.88 | J13: =I13/C13 -> 0.5405614
A14: Agresivo | B14: Año 2 | C14: =SUM(Mensual_Agresivo!D17:D28) -> 551890.21 | D14: =SUM(Mensual_Agresivo!G17:G28) -> 45990.851 | E14: =SUM(Mensual_Agresivo!H17:H28) -> 36000 | F14: =SUM(Mensual_Agresivo!F17:F28) -> 51300 | G14: =C14-D14-E14 -> 469899.36 | H14: =G14/C14 -> 0.8514363 | I14: =G14-F14 -> 418599.36 | J14: =I14/C14 -> 0.75848303
A15: Agresivo | B15: Año 3 | C15: =SUM(Mensual_Agresivo!D29:D40) -> 818624.22 | D15: =SUM(Mensual_Agresivo!G29:G40) -> 68218.685 | E15: =SUM(Mensual_Agresivo!H29:H40) -> 36000 | F15: =SUM(Mensual_Agresivo!F29:F40) -> 51300 | G15: =C15-D15-E15 -> 714405.53 | H15: =G15/C15 -> 0.87269045 | I15: =G15-F15 -> 663105.53 | J15: =I15/C15 -> 0.81002433

Sheet Unit Economics
A1: UNIT ECONOMICS
A2: LTV, CAC y periodo de recuperación por escenario · fórmulas ligadas a Supuestos
A3: Fórmulas: vida media = 1 / churn mensual · LTV = ARPU × vida media · Payback = CAC / margen de contribución mensual.
A5: Métrica | B5: Conservador | C5: Base | D5: Agresivo
A6: ARPU mensual | B6: =Supuestos!B10 -> 45 | C6: =Supuestos!C10 -> 49 | D6: =Supuestos!D10 -> 60
A7: CAC | B7: =Supuestos!B11 -> 150 | C7: =Supuestos!C11 -> 120 | D7: =Supuestos!D11 -> 95
A8: Churn mensual | B8: =Supuestos!B9 -> 0.035 | C8: =Supuestos!C9 -> 0.02 | D8: =Supuestos!D9 -> 0.015
A9: Vida media estimada (meses) | B9: =1/B8 -> 28.571429 | C9: =1/C8 -> 50 | D9: =1/D8 -> 66.666667
A10: Margen de contribución mensual (ARPU − infra) | B10: =B6-Supuestos!B12 -> 40 | C10: =C6-Supuestos!C12 -> 44 | D10: =D6-Supuestos!D12 -> 55
A11: LTV bruto (ARPU × vida media) | B11: =B6*B9 -> 1285.7143 | C11: =C6*C9 -> 2450 | D11: =D6*D9 -> 4000
A12: LTV neto (margen contribución × vida media) | B12: =B10*B9 -> 1142.8571 | C12: =C10*C9 -> 2200 | D12: =D10*D9 -> 3666.6667
A13: Ratio LTV:CAC (neto) | B13: =B12/B7 -> 7.6190476 | C13: =C12/C7 -> 18.333333 | D13: =D12/D7 -> 38.596491
A14: Periodo de recuperación del CAC (meses) | B14: =B7/B10 -> 3.75 | C14: =C7/C10 -> 2.7272727 | D14: =D7/D10 -> 1.7272727
A16: Lectura
A17: Un ratio LTV:CAC superior a 3x se considera saludable en SaaS B2B. Las cifras de este modelo superan ese umbral incluso en el escenario Conservador, pero CAC y churn son hipótesis de modelo, no datos observados: deben tratarse como objetivo de validación con las primeras cohortes reales, no como resultado garantizado.

Sheet Escenarios
A1: COMPARATIVA DE ESCENARIOS · ARR DE CIERRE
A2: ARR (run-rate anualizado) al cierre de cada año, por escenario · ligado a las hojas mensuales
A4: Año | B4: Conservador | C4: Base | D4: Agresivo
A5: Año 1 | B5: =Mensual_Conservador!E16 -> 71280.108 | C5: =Mensual_Base!E16 -> 149657.24 | D5: =Mensual_Agresivo!E16 -> 388303.7
A6: Año 2 | B6: =Mensual_Conservador!E28 -> 100156.07 | C6: =Mensual_Base!E28 -> 244025.1 | D6: =Mensual_Agresivo!E28 -> 682171.48
A7: Año 3 | B7: =Mensual_Conservador!E40 -> 118986.67 | C7: =Mensual_Base!E40 -> 318077.15 | D7: =Mensual_Agresivo!E40 -> 927295.99
A9: ARR de cierre de año = MRR del último mes del año × 12 (run-rate, no ingreso real cobrado en el año; ver hoja P&L Anual para ingreso real).

Sheet Use of Funds
A1: USE OF FUNDS
A2: Asignación del capital por tramo de inversión · importes y porcentajes
A4: Categoría | B4: 50.000€ | C4: 100.000€ | D4: 250.000€ | E4: 500.000€
A5: Producto | B5: 20000 | C5: 35000 | D5: 75000 | E5: 125000
A6: Marketing | B6: 12500 | C6: 30000 | D6: 87500 | E6: 175000
A7: Equipo | B7: 10000 | C7: 20000 | D7: 62500 | E7: 150000
A8: Operaciones | B8: 5000 | C8: 10000 | D8: 25000 | E8: 50000
A9: Reserva | B9: 2500 | C9: 5000 | D9: 0 | E9: 0
A10: TOTAL | B10: =SUM(B5:B9) -> 50000 | C10: =SUM(C5:C9) -> 100000 | D10: =SUM(D5:D9) -> 250000 | E10: =SUM(E5:E9) -> 500000
A12: % sobre el total del tramo
A13: Categoría | B13: 50.000€ | C13: 100.000€ | D13: 250.000€ | E13: 500.000€
A14: Producto | B14: =B5/B10 -> 0.4 | C14: =C5/C10 -> 0.35 | D14: =D5/D10 -> 0.3 | E14: =E5/E10 -> 0.25
A15: Marketing | B15: =B6/B10 -> 0.25 | C15: =C6/C10 -> 0.3 | D15: =D6/D10 -> 0.35 | E15: =E6/E10 -> 0.35
A16: Equipo | B16: =B7/B10 -> 0.2 | C16: =C7/C10 -> 0.2 | D16: =D7/D10 -> 0.25 | E16: =E7/E10 -> 0.3
A17: Operaciones | B17: =B8/B10 -> 0.1 | C17: =C8/C10 -> 0.1 | D17: =D8/D10 -> 0.1 | E17: =E8/E10 -> 0.1
A18: Reserva | B18: =B9/B10 -> 0.05 | C18: =C9/C10 -> 0.05 | D18: =D9/D10 -> 0 | E18: =E9/E10 -> 0
A20: Objetivo principal por tramo
A21: Importe | B21: Objetivo principal
A22: 50.000€ | B22: Alcanzar Product-Market Fit: completar la Base Maestra crítica y validar retención con las primeras cohortes reales.
A23: 100.000€ | B23: Llegar a 100 clientes de pago con un canal de adquisición ya repetible.
A24: 250.000€ | B24: Financiar la expansión a Iberia (Portugal): adaptación de producto, certificación fiscal y primer equipo comercial local.
A25: 500.000€ | B25: Financiar la entrada en LATAM (México): adaptación a CFDI, equipo local y primer ciclo de adquisición fuera de España.
A27: Nota: se ha añadido una línea de Reserva (5%) en los tramos de 50.000€ y 100.000€ para que la suma de categorías coincida exactamente con el importe levantado; en los tramos de 250.000€ y 500.000€ la asignación original ya sumaba el 100%.

Sheet Notas y Fuentes
A1: NOTAS METODOLÓGICAS Y FUENTES
A2: Documentación de supuestos, correcciones y trazabilidad del modelo
A3: Cambios respecto a la versión anterior del modelo
A5: 1. Los tres escenarios (Conservador / Base / Agresivo) ahora comparten el mismo motor de cálculo mensual y solo difieren en sus supuestos de entrada (altas mensuales, churn, ARPU, CAC). En la versión anterior, el resumen de escenarios (450.000€ / 1.200.000€ / 2.500.000€ de ARR a 3 años) era una estimación independiente, no derivada del modelo mensual detallado, lo que generaba una inconsistencia entre ambas cifras.
A7: 2. Con los supuestos reconstruidos, el ARR de cierre de año 3 resultante es de aproximadamente 119.000€ (Conservador), 318.000€ (Base) y 927.000€ (Agresivo). Estas cifras son inferiores a las de la versión anterior, pero sí están completamente trazadas y son recalculables si cambian los supuestos.
A9: 3. Se ha incorporado el coste de adquisición (CAC) a la cuenta de resultados anual. La versión anterior calculaba el EBITDA sin restar el gasto de CAC, lo que sobrestimaba la rentabilidad real. El modelo actual muestra ambas métricas por separado y claramente etiquetadas: «EBITDA antes de CAC» (capacidad de generación de caja del negocio ya instalado) y «EBITDA incl. CAC» (rentabilidad real dado el ritmo de inversión en crecimiento elegido).
A11: 4. Se ha añadido una línea de «Reserva» del 5% en los tramos de Use of Funds de 50.000€ y 100.000€, donde la suma original de categorías no llegaba al importe total levantado.
A14: Fuentes de los supuestos clave
A15: Dato | B15: Valor | C15: Fuente
A16: Autónomos registrados en España | B16: 3.431.797 (31/12/2025) | C16: Ministerio de Trabajo y Economía Social / Infoautonomos, datos oficiales, en máximos históricos.
A17: Adopción de IA entre autónomos | B17: 20% usa IA de forma habitual | C17: UPTA (Unión de Profesionales y Trabajadores Autónomos), análisis publicado junio 2026.
A18: Empresas del sector de instalaciones eléctricas | B18: 10.300 empresas · ≈19.300M€ de facturación 2023 (1,29% del PIB) | C18: Guía de Empresas Instaladoras del Sector Eléctrico, C de Comunicación.
A19: Salarios de electricistas y fontaneros autónomos | B19: Electricistas 2.500–3.500€/mes · Fontaneros 2.000–3.500€/mes | C19: Cronoshare, recogido por Infobae, noviembre 2025.
A20: Plazo VeriFactu | B20: Sociedades: 1 ene 2027 · Autónomos: 1 jul 2027 | C20: RD 1007/2023, modificado por el RDL 15/2025 de 2 de diciembre.
A21: Kit Digital — reactivación 2026 | B21: Bonos de hasta 12.000–19.000€, fondos remanentes, sin fecha de cierre fija | C21: Orden TDF/39/2026, BOE 28 de enero de 2026.
A22: Precio plan Profesional TrabFlow | B22: 49€/mes | C22: Tarifa pública TrabFlow (usada como ARPU base del modelo).
A23: ServiceTitan (referencia de categoría, EE. UU.) | B23: ≈7.000M$ capitalización · ≈1.000M$ ingresos anuales | C23: Datos públicos de mercado, mediados de 2026.
A24: Jobber (referencia de categoría, EE. UU./Canadá) | B24: 167,5M$ de ingresos (2024) · 100.000+ clientes | C24: Estimaciones públicas (Sacra, Tracxn).
A26: CAC y churn son hipótesis de planificación, no datos medidos con clientes de pago de TrabFlow. Deben revisarse en cuanto existan las primeras cohortes reales.
